{
  "1": {
    "value": "1",
    "type": "borderWidth"
  },
  "2": {
    "value": "2",
    "type": "borderWidth"
  },
  "3": {
    "value": "3",
    "type": "borderWidth"
  },
  "4": {
    "value": "4",
    "type": "borderRadius"
  },
  "8": {
    "value": "8",
    "type": "borderRadius"
  },
  "12": {
    "value": "12",
    "type": "borderRadius"
  },
  "16": {
    "value": "16",
    "type": "borderRadius"
  },
  "24": {
    "value": "24",
    "type": "borderRadius"
  },
  "40": {
    "value": "0.4",
    "type": "opacity"
  },
  "60": {
    "value": "0.6",
    "type": "opacity"
  },
  "100": {
    "value": "100",
    "type": "borderRadius"
  },
  "size": {
    "0": {
      "value": "0",
      "type": "sizing"
    },
    "8": {
      "value": "8",
      "type": "sizing"
    },
    "12": {
      "value": "12",
      "type": "sizing"
    },
    "16": {
      "value": "16",
      "type": "sizing"
    },
    "18": {
      "value": "18",
      "type": "sizing"
    },
    "20": {
      "value": "20",
      "type": "sizing"
    },
    "24": {
      "value": "24",
      "type": "sizing"
    },
    "28": {
      "value": "28",
      "type": "sizing"
    },
    "32": {
      "value": "32",
      "type": "sizing"
    },
    "40": {
      "value": "40",
      "type": "sizing"
    },
    "48": {
      "value": "48",
      "type": "sizing"
    },
    "56": {
      "value": "56",
      "type": "sizing"
    },
    "64": {
      "value": "64",
      "type": "sizing"
    },
    "72": {
      "value": "72",
      "type": "sizing"
    },
    "80": {
      "value": "80",
      "type": "sizing"
    }
  },
  "spacing": {
    "0": {
      "value": "0",
      "type": "spacing"
    },
    "2": {
      "value": "2",
      "type": "spacing"
    },
    "4": {
      "value": "4",
      "type": "spacing"
    },
    "6": {
      "value": "6",
      "type": "spacing"
    },
    "8": {
      "value": "8",
      "type": "spacing"
    },
    "12": {
      "value": "12",
      "type": "spacing"
    },
    "16": {
      "value": "16",
      "type": "spacing"
    },
    "24": {
      "value": "24",
      "type": "spacing"
    },
    "32": {
      "value": "32",
      "type": "spacing"
    },
    "40": {
      "value": "40",
      "type": "spacing"
    },
    "48": {
      "value": "48",
      "type": "spacing"
    },
    "56": {
      "value": "56",
      "type": "spacing"
    },
    "64": {
      "value": "64",
      "type": "spacing"
    },
    "72": {
      "value": "72",
      "type": "spacing"
    },
    "80": {
      "value": "80",
      "type": "spacing"
    },
    "88": {
      "value": "88",
      "type": "spacing"
    },
    "96": {
      "value": "96",
      "type": "spacing"
    },
    "104": {
      "value": "104",
      "type": "spacing"
    },
    "112": {
      "value": "112",
      "type": "spacing"
    },
    "120": {
      "value": "120",
      "type": "spacing"
    }
  },
  "shadow8": {
    "value": [
      {
        "color": "#00000021",
        "type": "dropShadow",
        "x": "0",
        "y": "1.600000023841858",
        "blur": "3.5999999046325684",
        "spread": "0"
      },
      {
        "color": "#0000001a",
        "type": "dropShadow",
        "x": "0",
        "y": "0.30000001192092896",
        "blur": "0.8999999761581421",
        "spread": "0"
      }
    ],
    "type": "boxShadow",
    "description": "Cards"
  },
  "shadow16": {
    "value": [
      {
        "color": "#00000021",
        "type": "dropShadow",
        "x": "0",
        "y": "3.200000047683716",
        "blur": "7.199999809265137",
        "spread": "0"
      },
      {
        "color": "#0000001a",
        "type": "dropShadow",
        "x": "0",
        "y": "0.6000000238418579",
        "blur": "1.7999999523162842",
        "spread": "0"
      }
    ],
    "type": "boxShadow",
    "description": "Tooltips"
  },
  "shadow24": {
    "value": [
      {
        "color": "#00000021",
        "type": "dropShadow",
        "x": "0",
        "y": "6.400000095367432",
        "blur": "14.399999618530273",
        "spread": "0"
      },
      {
        "color": "#0000001a",
        "type": "dropShadow",
        "x": "0",
        "y": "1.2000000476837158",
        "blur": "3.5999999046325684",
        "spread": "0"
      }
    ],
    "type": "boxShadow",
    "description": "Panels"
  },
  "shadow32": {
    "value": [
      {
        "color": "#00000038",
        "type": "dropShadow",
        "x": "0",
        "y": "25.600000381469727",
        "blur": "57.599998474121094",
        "spread": "0"
      },
      {
        "color": "#0000002e",
        "type": "dropShadow",
        "x": "0",
        "y": "4.800000190734863",
        "blur": "14.399999618530273",
        "spread": "0"
      }
    ],
    "type": "boxShadow",
    "description": "Modals"
  },
  "fontFamilies": {
    "segoe-ui": {
      "value": "Segoe UI",
      "type": "fontFamilies"
    }
  },
  "lineHeights": {
    "0": {
      "value": "AUTO",
      "type": "lineHeights"
    }
  },
  "fontWeights": {
    "segoe-ui-0": {
      "value": "Regular",
      "type": "fontWeights"
    },
    "segoe-ui-1": {
      "value": "Bold",
      "type": "fontWeights"
    },
    "segoe-ui-2": {
      "value": "Semibold",
      "type": "fontWeights"
    }
  },
  "fontSize": {
    "0": {
      "value": "12",
      "type": "fontSizes"
    },
    "1": {
      "value": "14",
      "type": "fontSizes"
    },
    "2": {
      "value": "16",
      "type": "fontSizes"
    },
    "3": {
      "value": "18",
      "type": "fontSizes"
    },
    "4": {
      "value": "20",
      "type": "fontSizes"
    },
    "5": {
      "value": "24",
      "type": "fontSizes"
    },
    "6": {
      "value": "34",
      "type": "fontSizes"
    },
    "7": {
      "value": "48",
      "type": "fontSizes"
    },
    "8": {
      "value": "60",
      "type": "fontSizes"
    },
    "9": {
      "value": "96",
      "type": "fontSizes"
    }
  },
  "letterSpacing": {
    "0": {
      "value": "-1.5%",
      "type": "letterSpacing"
    },
    "1": {
      "value": "-0.5%",
      "type": "letterSpacing"
    },
    "2": {
      "value": "0%",
      "type": "letterSpacing"
    },
    "3": {
      "value": "0.25%",
      "type": "letterSpacing"
    },
    "4": {
      "value": "0.15%",
      "type": "letterSpacing"
    },
    "5": {
      "value": "0.1%",
      "type": "letterSpacing"
    },
    "6": {
      "value": "0.5%",
      "type": "letterSpacing"
    },
    "7": {
      "value": "1.25%",
      "type": "letterSpacing"
    },
    "8": {
      "value": "1.5%",
      "type": "letterSpacing"
    }
  },
  "paragraphSpacing": {
    "0": {
      "value": "0",
      "type": "paragraphSpacing"
    }
  },
  "Segoe UI": {
    "H1": {
      "value": {
        "fontFamily": "{fontFamilies.segoe-ui}",
        "fontWeight": "{fontWeights.segoe-ui-0}",
        "lineHeight": "{lineHeights.0}",
        "fontSize": "{fontSize.9}",
        "letterSpacing": "{letterSpacing.0}",
        "paragraphSpacing": "{paragraphSpacing.0}",
        "textCase": "{textCase.none}",
        "textDecoration": "{textDecoration.none}"
      },
      "type": "typography"
    },
    "H2": {
      "value": {
        "fontFamily": "{fontFamilies.segoe-ui}",
        "fontWeight": "{fontWeights.segoe-ui-0}",
        "lineHeight": "{lineHeights.0}",
        "fontSize": "{fontSize.8}",
        "letterSpacing": "{letterSpacing.1}",
        "paragraphSpacing": "{paragraphSpacing.0}",
        "textCase": "{textCase.none}",
        "textDecoration": "{textDecoration.none}"
      },
      "type": "typography"
    },
    "H3": {
      "value": {
        "fontFamily": "{fontFamilies.segoe-ui}",
        "fontWeight": "{fontWeights.segoe-ui-2}",
        "lineHeight": "{lineHeights.0}",
        "fontSize": "{fontSize.7}",
        "letterSpacing": "{letterSpacing.2}",
        "paragraphSpacing": "{paragraphSpacing.0}",
        "textCase": "{textCase.none}",
        "textDecoration": "{textDecoration.none}"
      },
      "type": "typography"
    },
    "H4": {
      "value": {
        "fontFamily": "{fontFamilies.segoe-ui}",
        "fontWeight": "{fontWeights.segoe-ui-2}",
        "lineHeight": "{lineHeights.0}",
        "fontSize": "{fontSize.6}",
        "letterSpacing": "{letterSpacing.3}",
        "paragraphSpacing": "{paragraphSpacing.0}",
        "textCase": "{textCase.none}",
        "textDecoration": "{textDecoration.none}"
      },
      "type": "typography"
    },
    "H5": {
      "value": {
        "fontFamily": "{fontFamilies.segoe-ui}",
        "fontWeight": "{fontWeights.segoe-ui-2}",
        "lineHeight": "{lineHeights.0}",
        "fontSize": "{fontSize.5}",
        "letterSpacing": "{letterSpacing.2}",
        "paragraphSpacing": "{paragraphSpacing.0}",
        "textCase": "{textCase.none}",
        "textDecoration": "{textDecoration.none}"
      },
      "type": "typography"
    },
    "H6": {
      "value": {
        "fontFamily": "{fontFamilies.segoe-ui}",
        "fontWeight": "{fontWeights.segoe-ui-2}",
        "lineHeight": "{lineHeights.0}",
        "fontSize": "{fontSize.4}",
        "letterSpacing": "{letterSpacing.4}",
        "paragraphSpacing": "{paragraphSpacing.0}",
        "textCase": "{textCase.none}",
        "textDecoration": "{textDecoration.none}"
      },
      "type": "typography"
    },
    "Subtitle 1": {
      "value": {
        "fontFamily": "{fontFamilies.segoe-ui}",
        "fontWeight": "{fontWeights.segoe-ui-0}",
        "lineHeight": "{lineHeights.0}",
        "fontSize": "{fontSize.3}",
        "letterSpacing": "{letterSpacing.4}",
        "paragraphSpacing": "{paragraphSpacing.0}",
        "textCase": "{textCase.none}",
        "textDecoration": "{textDecoration.none}"
      },
      "type": "typography"
    },
    "Subtitle 2": {
      "value": {
        "fontFamily": "{fontFamilies.segoe-ui}",
        "fontWeight": "{fontWeights.segoe-ui-2}",
        "lineHeight": "{lineHeights.0}",
        "fontSize": "{fontSize.3}",
        "letterSpacing": "{letterSpacing.5}",
        "paragraphSpacing": "{paragraphSpacing.0}",
        "textCase": "{textCase.none}",
        "textDecoration": "{textDecoration.none}"
      },
      "type": "typography"
    },
    "Body 1": {
      "value": {
        "fontFamily": "{fontFamilies.segoe-ui}",
        "fontWeight": "{fontWeights.segoe-ui-0}",
        "lineHeight": "{lineHeights.0}",
        "fontSize": "{fontSize.2}",
        "letterSpacing": "{letterSpacing.6}",
        "paragraphSpacing": "{paragraphSpacing.0}",
        "textCase": "{textCase.none}",
        "textDecoration": "{textDecoration.none}"
      },
      "type": "typography"
    },
    "Body 2": {
      "value": {
        "fontFamily": "{fontFamilies.segoe-ui}",
        "fontWeight": "{fontWeights.segoe-ui-0}",
        "lineHeight": "{lineHeights.0}",
        "fontSize": "{fontSize.1}",
        "letterSpacing": "{letterSpacing.6}",
        "paragraphSpacing": "{paragraphSpacing.0}",
        "textCase": "{textCase.none}",
        "textDecoration": "{textDecoration.none}"
      },
      "type": "typography"
    },
    "Button": {
      "value": {
        "fontFamily": "{fontFamilies.segoe-ui}",
        "fontWeight": "{fontWeights.segoe-ui-0}",
        "lineHeight": "{lineHeights.0}",
        "fontSize": "{fontSize.1}",
        "letterSpacing": "{letterSpacing.3}",
        "paragraphSpacing": "{paragraphSpacing.0}",
        "textCase": "{textCase.none}",
        "textDecoration": "{textDecoration.none}"
      },
      "type": "typography"
    },
    "Button-Large": {
      "value": {
        "fontFamily": "{fontFamilies.segoe-ui}",
        "fontWeight": "{fontWeights.segoe-ui-0}",
        "lineHeight": "{lineHeights.0}",
        "fontSize": "{fontSize.2}",
        "letterSpacing": "{letterSpacing.3}",
        "paragraphSpacing": "{paragraphSpacing.0}",
        "textCase": "{textCase.none}",
        "textDecoration": "{textDecoration.none}"
      },
      "type": "typography"
    },
    "Caption 1": {
      "value": {
        "fontFamily": "{fontFamilies.segoe-ui}",
        "fontWeight": "{fontWeights.segoe-ui-0}",
        "lineHeight": "{lineHeights.0}",
        "fontSize": "{fontSize.0}",
        "letterSpacing": "{letterSpacing.6}",
        "paragraphSpacing": "{paragraphSpacing.0}",
        "textCase": "{textCase.none}",
        "textDecoration": "{textDecoration.none}"
      },
      "type": "typography"
    },
    "Overline": {
      "value": {
        "fontFamily": "{fontFamilies.segoe-ui}",
        "fontWeight": "{fontWeights.segoe-ui-2}",
        "lineHeight": "{lineHeights.0}",
        "fontSize": "{fontSize.0}",
        "letterSpacing": "{letterSpacing.8}",
        "paragraphSpacing": "{paragraphSpacing.0}",
        "textCase": "{textCase.uppercase}",
        "textDecoration": "{textDecoration.none}"
      },
      "type": "typography"
    }
  },
  "textCase": {
    "none": {
      "value": "none",
      "type": "textCase"
    },
    "uppercase": {
      "value": "uppercase",
      "type": "textCase"
    }
  },
  "textDecoration": {
    "none": {
      "value": "none",
      "type": "textDecoration"
    }
  },
  "brand-color-outline": {
    "value": {
      "x": "0",
      "y": "0",
      "blur": "0",
      "spread": "2",
      "color": "{shadow.brand}",
      "type": "dropShadow"
    },
    "type": "boxShadow"
  },
  "primary-color-outline": {
    "value": {
      "x": "0",
      "y": "0",
      "blur": "0",
      "spread": "2",
      "color": "{shadow.primary}",
      "type": "dropShadow"
    },
    "type": "boxShadow"
  },
  "error-color-outline": {
    "value": {
      "x": "0",
      "y": "0",
      "blur": "0",
      "spread": "2",
      "color": "{shadow.error}",
      "type": "innerShadow"
    },
    "type": "boxShadow"
  },
  "brand-focus": {
    "value": {
      "x": "0",
      "y": "0",
      "blur": "0",
      "spread": "2",
      "color": "{shadow.brand}",
      "type": "dropShadow"
    },
    "type": "boxShadow"
  }
}